jclublauncher
setup.py
jclubtool/__init__.py
jclubtool/app.py
jclubtool/guitools.py
jclubtool/io.py
jclubtool/pages.py
jclubtool.egg-info/PKG-INFO
jclubtool.egg-info/SOURCES.txt
jclubtool.egg-info/dependency_links.txt
jclubtool.egg-info/not-zip-safe
jclubtool.egg-info/requires.txt
jclubtool.egg-info/top_level.txt