Metadata-Version: 1.0
Name: jclubtool
Version: 0.1
Summary: Python 3 PDF Reader and Image Snippet Collection Tool
Home-page: http://github.com/neuroneuro15/jclubtool
Author: Nicholas A Del Grosso
Author-email: delgrosso.nick@gmail.com
License: MIT
Platform: UNKNOWN
